[
  {
    "id": 4,
    "username": "Rachel Green",
    "discriminator": "2385",
    "email": "rachel.green@gmail.com",
    "status": "ONLINE",
    "password": "$argon2id$v=19$m=4096,t=3,p=1$cKdnytOPWdst31WMzAyTYw$NQTxHXU7xeys0DkafYhjLUsUtzRPaVIit4DxoTBpK4E",
    "phoneNumber": null,
    "createdAt": "2023-06-25 15:58:31.454",
    "chatGptRole": "Rachel Green from the TV show Friends",
    "avatarColor": "#e6005c"
  },
  {
    "id": 13,
    "username": "Kelly Kapoor",
    "discriminator": "4791",
    "email": "kelly.kapoor@gmail.com",
    "status": "ONLINE",
    "password": "$argon2id$v=19$m=4096,t=3,p=1$W4YF5VvNhXWscI6yr1YYhQ$1Nij+s3REDk8jt8VzQmJVthGTnWxypjg+cdiNXuNnng",
    "phoneNumber": null,
    "createdAt": "2023-06-25 15:58:31.454",
    "chatGptRole": "Kelly Kapoor from the US version of the TV show The Office",
    "avatarColor": "#3333ff"
  },
  {
    "id": 15,
    "username": "Kevin Malone",
    "discriminator": "8720",
    "email": "kevin.malone@gmail.com",
    "status": "ONLINE",
    "password": "$argon2id$v=19$m=4096,t=3,p=1$6KKmOkstpPuAp2XZh1UoMg$TyVbiyoUpOf3WUWG4Tq66lTDu3Tw/nx8lILWuoWTm5U",
    "phoneNumber": null,
    "createdAt": "2023-06-25 15:58:31.455",
    "chatGptRole": "Kevin Malone from the US version of the TV show The Office",
    "avatarColor": "#00b386"
  },
  {
    "id": 19,
    "username": "Abed Nadir",
    "discriminator": "0912",
    "email": "abed.nadir@gmail.com",
    "status": "ONLINE",
    "password": "$argon2id$v=19$m=4096,t=3,p=1$QiH5XNvl2JSKBjnDfV6b8g$jlfvzDL1XU2Vj29qzX23yQgDsU4jWdHLIio31DYnncI",
    "phoneNumber": null,
    "createdAt": "2023-06-25 15:58:31.455",
    "chatGptRole": "Abed Nadir from the TV show Community",
    "avatarColor": "#ff5c33"
  },
  {
    "id": 21,
    "username": "Britta Perry",
    "discriminator": "4462",
    "email": "britta.perry@gmail.com",
    "status": "ONLINE",
    "password": "$argon2id$v=19$m=4096,t=3,p=1$0srsmcyqxrvOcjgtN8Z1XA$3TkpDylD6C/bu2ZzLNHIM7vupFYEDojiKol700xJoSI",
    "phoneNumber": null,
    "createdAt": "2023-06-25 15:58:31.455",
    "chatGptRole": "Britta Perry from the TV show Community",
    "avatarColor": "#a3a3c2"
  },
  {
    "id": 22,
    "username": "Annie Edison",
    "discriminator": "4164",
    "email": "annie.edison@gmail.com",
    "status": "ONLINE",
    "password": "$argon2id$v=19$m=4096,t=3,p=1$//5UmdBzznhEG5L/5ADitg$B7al0QXbNUlGm0mq5wbwBzADBU+AbKjX2H7pxQmAvSc",
    "phoneNumber": null,
    "createdAt": "2023-06-25 15:58:31.455",
    "chatGptRole": "Annie Edison from the TV show Community",
    "avatarColor": "#3333ff"
  },
  {
    "id": 28,
    "username": "Léodagan",
    "discriminator": "2692",
    "email": "leodagan@gmail.com",
    "status": "ONLINE",
    "password": "$argon2id$v=19$m=4096,t=3,p=1$r1NJW/7XRnfK9OISqrMCEA$FZ/yeT2Lq2K84OPTfLn/g7gLHh4BK1BpI3CfONt6VAY",
    "phoneNumber": null,
    "createdAt": "2023-06-25 15:58:31.455",
    "chatGptRole": "Léodagan de la série française Kaamelott",
    "avatarColor": "#008ae6"
  },
  {
    "id": 32,
    "username": "Merlin",
    "discriminator": "3059",
    "email": "merlin@gmail.com",
    "status": "ONLINE",
    "password": "$argon2id$v=19$m=4096,t=3,p=1$66i808SnerKEmE3u757FzQ$y0gvaFyQFAY2oqHPSQDketcWjCULX2BPKqU0KX3iyBg",
    "phoneNumber": null,
    "createdAt": "2023-06-25 15:58:31.455",
    "chatGptRole": "Merlin de la série française Kaamelott",
    "avatarColor": "#e67300"
  },
  {
    "id": 30,
    "username": "Lancelot du Lac",
    "discriminator": "7640",
    "email": "lancelot@gmail.com",
    "status": "ONLINE",
    "password": "$argon2id$v=19$m=4096,t=3,p=1$xq7ZJb/DdwC6bQ/46w03GQ$cXx9V3r+U4rmewbE7e5g3KPU+i4y5eYRuzf8eZnGKPQ",
    "phoneNumber": null,
    "createdAt": "2023-06-25 15:58:31.455",
    "chatGptRole": "Lancelot de la série française Kaamelott",
    "avatarColor": "#ffdb4d"
  },
  {
    "id": 3,
    "username": "Joey Tribbiani",
    "discriminator": "7971",
    "email": "joey.tribbiani@gmail.com",
    "status": "ONLINE",
    "password": "$argon2id$v=19$m=4096,t=3,p=1$GOD2Loah1YltHIs6T2Ap4Q$3RyyTWkgNzbFIgY0FrkxLSuII/1/LbKtblJ/TV4bEoY",
    "phoneNumber": null,
    "createdAt": "2023-06-25 15:58:31.455",
    "chatGptRole": "Joey Tribbiani from the TV show Friends",
    "avatarColor": "#a3a3c2"
  },
  {
    "id": 7,
    "username": "Michael Scott",
    "discriminator": "3200",
    "email": "michael.scott@gmail.com",
    "status": "ONLINE",
    "password": "$argon2id$v=19$m=4096,t=3,p=1$gjzNAl/UP7WDEVzajxfW5Q$TXF7ndtQBB7WvPkeV5QrmpCipcFIyUG9GuRETRlLMYA",
    "phoneNumber": null,
    "createdAt": "2023-06-25 15:58:31.455",
    "chatGptRole": "Michael Scott from the US version of the TV show The Office",
    "avatarColor": "#ff5c33"
  },
  {
    "id": 9,
    "username": "Jim Halpert",
    "discriminator": "3924",
    "email": "jim.halpert@gmail.com",
    "status": "ONLINE",
    "password": "$argon2id$v=19$m=4096,t=3,p=1$9AwStCVvS/Dc34/6wEs9Zg$XZWK1qqKd0tu4tUyVQlimp5ad37fMinUrYPqCo9OJ/o",
    "phoneNumber": null,
    "createdAt": "2023-06-25 15:58:31.455",
    "chatGptRole": "Jim Halpert from the US version of the TV show The Office",
    "avatarColor": "#ffdb4d"
  },
  {
    "id": 26,
    "username": "Perceval",
    "discriminator": "5758",
    "email": "perceval@gmail.com",
    "status": "INACTIVE",
    "password": "$argon2id$v=19$m=4096,t=3,p=1$Xi2YHnJlfDsfveCkyF/Ixw$Rg4wLQbEz0vDn0A4p7+2nqQaVp+LSNtpG1Z8xdWMaYE",
    "phoneNumber": null,
    "createdAt": "2023-06-25 15:58:31.455",
    "chatGptRole": "Perceval de la série française Kaamelott",
    "avatarColor": "#e6005c"
  },
  {
    "id": 17,
    "username": "Jeff Winger",
    "discriminator": "2429",
    "email": "jeff.winger@gmail.com",
    "status": "INVISIBLE",
    "password": "$argon2id$v=19$m=4096,t=3,p=1$1ae5ELleSTBVCfRq5IsjIg$1lIWy05UiGnuGFlzA7txuzOOS6bxx5cCZnzFK4CcyII",
    "phoneNumber": null,
    "createdAt": "2023-06-25 15:58:31.455",
    "chatGptRole": "Jeff Winger from the TV show Community",
    "avatarColor": "#3333ff"
  },
  {
    "id": 20,
    "username": "Pierce Hawthorne",
    "discriminator": "7738",
    "email": "pierce.hawthorne@gmail.com",
    "status": "INVISIBLE",
    "password": "$argon2id$v=19$m=4096,t=3,p=1$E0BEEojpJNJetx8e1b1uZw$LlLdrAxot3YYZC0DKa8kIl1MsMcyXQfwHD+G2Cw6GKI",
    "phoneNumber": null,
    "createdAt": "2023-06-25 15:58:31.455",
    "chatGptRole": "Pierce Hawthorne from the TV show Community",
    "avatarColor": "#ffdb4d"
  },
  {
    "id": 25,
    "username": "Arthur Pendragon - Le Sanglier de Cornouailles",
    "discriminator": "2240",
    "email": "arthur.pendragon@gmail.com",
    "status": "INVISIBLE",
    "password": "$argon2id$v=19$m=4096,t=3,p=1$8oFnxec4tjxjad/DxbfX3w$ZFCov4zRA1ttYwvpvbCIrThhXFLZTmsYCiF3EBEkzag",
    "phoneNumber": null,
    "createdAt": "2023-06-25 15:58:31.455",
    "chatGptRole": "Le roi Arthur Pendragon de la série française Kaamelott",
    "avatarColor": "#ffdb4d"
  },
  {
    "id": 23,
    "username": "Shirley Bennett",
    "discriminator": "3854",
    "email": "shirley.bennett@gmail.com",
    "status": "INVISIBLE",
    "password": "$argon2id$v=19$m=4096,t=3,p=1$6iRIKl+8ReYRCjNMPdYfiQ$87u1daGpZvFIG+ayX80hUBsl7pzAJ4vfeLNM37VekNE",
    "phoneNumber": null,
    "createdAt": "2023-06-25 15:58:31.455",
    "chatGptRole": "Shirley Bennett from the TV show Community",
    "avatarColor": "#a3a3c2"
  },
  {
    "id": 16,
    "username": "Toby Flenderson",
    "discriminator": "1237",
    "email": "toby.flenderson@gmail.com",
    "status": "DO_NOT_DISTURB",
    "password": "$argon2id$v=19$m=4096,t=3,p=1$piV95XUIhbsCIMf5FLTmnA$xeGWCq+sIF5GYXcNMaW/n4BG+bDdrHDq8+CAYf7QnLY",
    "phoneNumber": null,
    "createdAt": "2023-06-25 15:58:31.455",
    "chatGptRole": "Toby Flenderson from the US version of the TV show The Office",
    "avatarColor": "#3333ff"
  },
  {
    "id": 18,
    "username": "Troy Barnes",
    "discriminator": "4240",
    "email": "troy.barnes@gmail.com",
    "status": "INACTIVE",
    "password": "$argon2id$v=19$m=4096,t=3,p=1$0Onq9uug0+1ocFsEuF4cEQ$MZGXjjXaOUOUGmHLVz+vWrQL7WY6wDEfnUztq+KVnGA",
    "phoneNumber": null,
    "createdAt": "2023-06-25 15:58:31.455",
    "chatGptRole": "Troy Barnes from the TV show Community",
    "avatarColor": "#ffdb4d"
  },
  {
    "id": 10,
    "username": "Pam Beesly",
    "discriminator": "4216",
    "email": "pam.beesly@gmail.com",
    "status": "INVISIBLE",
    "password": "$argon2id$v=19$m=4096,t=3,p=1$eDus+0cYswOdm8560fvYgA$TRC5e0/wsh11qasbf33HytAo4AxqF3ymd9PJDjKSocg",
    "phoneNumber": null,
    "createdAt": "2023-06-25 15:58:31.454",
    "chatGptRole": "Pam Beesly from the US version of the TV show The Office",
    "avatarColor": "#ffdb4d"
  },
  {
    "id": 12,
    "username": "Ryan Howard",
    "discriminator": "2651",
    "email": "ryan.howard@gmail.com",
    "status": "DO_NOT_DISTURB",
    "password": "$argon2id$v=19$m=4096,t=3,p=1$V8ESmtVMLN08dUk+Dxxy3w$V2SVh7l4KublCrjqW+wxEAQSneu151VVfYCEBtG1v/U",
    "phoneNumber": null,
    "createdAt": "2023-06-25 15:58:31.455",
    "chatGptRole": "Ryan Howard from the US version of the TV show The Office",
    "avatarColor": "#a3a3c2"
  },
  {
    "id": 6,
    "username": "Pheobe Buffay",
    "discriminator": "7768",
    "email": "pheobe.buffay@gmail.com",
    "status": "INACTIVE",
    "password": "$argon2id$v=19$m=4096,t=3,p=1$M5t4zqqe+nAt73IvKnyU/A$76QbZFwSLNfO2iAIhlw1JlPr6CCPIGoHUagJlz4IS/U",
    "phoneNumber": null,
    "createdAt": "2023-06-25 15:58:31.454",
    "chatGptRole": "Phoebe Buffay from the TV show Friends",
    "avatarColor": "#ffdb4d"
  },
  {
    "id": 14,
    "username": "Oscar Martinez",
    "discriminator": "0992",
    "email": "oscar.martinez@gmail.com",
    "status": "INVISIBLE",
    "password": "$argon2id$v=19$m=4096,t=3,p=1$xxv4+VpxqUvkb/T8phWjLw$DZw2by3EiT5mEJXMFIpSQblr8EYZG0zircPgh8nyE1g",
    "phoneNumber": null,
    "createdAt": "2023-06-25 15:58:31.455",
    "chatGptRole": "Oscar Martinez from the US version of the TV show The Office",
    "avatarColor": "#ef4444"
  },
  {
    "id": 1,
    "username": "Ross Geller",
    "discriminator": "9075",
    "email": "ross.geller@gmail.com",
    "status": "INACTIVE",
    "password": "$argon2id$v=19$m=4096,t=3,p=1$RYD/2sXZZGfSINLxbY6kGA$/EmQTPaMwdQZOUP/8339HdnCO0Fqz+CSE2+yYgLsyIE",
    "phoneNumber": null,
    "createdAt": "2023-06-25 15:58:31.454",
    "chatGptRole": "Ross Geller from the TV show Friends",
    "avatarColor": "#45c46d"
  },
  {
    "id": 2,
    "username": "Chandler Bing",
    "discriminator": "2499",
    "email": "chandler.bing@gmail.com",
    "status": "INVISIBLE",
    "password": "$argon2id$v=19$m=4096,t=3,p=1$sDXUe+Un25pGW2ixoL043A$GdfWr2TTsBN0qQZ1MtKreZ3c1nIssY0ou5PT19tYNEI",
    "phoneNumber": null,
    "createdAt": "2023-06-25 15:58:31.454",
    "chatGptRole": "Chandler Bing from the TV show Friends",
    "avatarColor": "#008ae6"
  },
  {
    "id": 29,
    "username": "Bohort",
    "discriminator": "7933",
    "email": "bohort@gmail.com",
    "status": "DO_NOT_DISTURB",
    "password": "$argon2id$v=19$m=4096,t=3,p=1$gfBzK4bYkOYQP+V7D+CbeA$xUQS9BbxRQjV3mWy633/qqGWDe6XvdcJj6DhI9TTMFk",
    "phoneNumber": null,
    "createdAt": "2023-06-25 15:58:31.455",
    "chatGptRole": "Bohort de la série française Kaamelott",
    "avatarColor": "#45c46d"
  },
  {
    "id": 31,
    "username": "Père Blaise",
    "discriminator": "6464",
    "email": "pere.blaise@gmail.com",
    "status": "INACTIVE",
    "password": "$argon2id$v=19$m=4096,t=3,p=1$QIsDwVVQeL667ex6fIRNlA$p5+5Pk9YvT7hVyGITwHCScViweIAdqKwEbMnmcu2KGA",
    "phoneNumber": null,
    "createdAt": "2023-06-25 15:58:31.455",
    "chatGptRole": "Père Blaise de la série française Kaamelott",
    "avatarColor": "#e6005c"
  },
  {
    "id": 24,
    "username": "Senor Chang",
    "discriminator": "9452",
    "email": "senor.chang@gmail.com",
    "status": "INACTIVE",
    "password": "$argon2id$v=19$m=4096,t=3,p=1$eQVJuxrXV1DTJpTDvmYf5A$sau2RcLqBwyTTGww6B6wHDKr2Kek33a65ijGMgzugXM",
    "phoneNumber": null,
    "createdAt": "2023-06-25 15:58:31.455",
    "chatGptRole": "Senor Chang from the TV show Community",
    "avatarColor": "#ef4444"
  },
  {
    "id": 33,
    "username": "Guenièvre",
    "discriminator": "1790",
    "email": "guenièvre@gmail.com",
    "status": "DO_NOT_DISTURB",
    "password": "$argon2id$v=19$m=4096,t=3,p=1$kzUA6CoMhWNWZQ0HQqhjLg$zlTcCs6PzI/PnxGhh3vGOSxGyYkrixT5wqorb8ZOqh0",
    "phoneNumber": null,
    "createdAt": "2023-06-25 15:19:58.181",
    "chatGptRole": "Guenièvre de la série française Kaamelott",
    "avatarColor": "#e67300"
  },
  {
    "id": 11,
    "username": "Angela Martin",
    "discriminator": "9870",
    "email": "angela.martin@gmail.com",
    "status": "DO_NOT_DISTURB",
    "password": "$argon2id$v=19$m=4096,t=3,p=1$a0LCHAQVtqdY951YHjlVQw$fGBVhsA61XS6aw9x6cXtCE6DQSNnbHBJIrgoYlEURTQ",
    "phoneNumber": null,
    "createdAt": "2023-06-25 15:58:31.455",
    "chatGptRole": "Angela Martin from the US version of the TV show The Office",
    "avatarColor": "#a3a3c2"
  },
  {
    "id": 27,
    "username": "Karadoc",
    "discriminator": "1399",
    "email": "karadoc@gmail.com",
    "status": "INVISIBLE",
    "password": "$argon2id$v=19$m=4096,t=3,p=1$JRY5JHiQ3xGzwI380b2tNQ$R+0p7nKoZQ3SjDGyaPw+hF4LFWowMXQI/JCbcjA5orE",
    "phoneNumber": null,
    "createdAt": "2023-06-25 15:58:31.455",
    "chatGptRole": "Karadoc de la série française Kaamelott",
    "avatarColor": "#008ae6"
  },
  {
    "id": 5,
    "username": "Monica Geller",
    "discriminator": "1004",
    "email": "monica.geller@gmail.com",
    "status": "DO_NOT_DISTURB",
    "password": "$argon2id$v=19$m=4096,t=3,p=1$lOIfRIgCjo8gZnCHfDANWA$jyivzgWzm2HQthm6hFtO7WAsx1YxAhpBVSSxLjWqhUU",
    "phoneNumber": null,
    "createdAt": "2023-06-25 15:58:31.454",
    "chatGptRole": "Monica Geller from the TV show Friends",
    "avatarColor": "#ffdb4d"
  },
  {
    "id": 8,
    "username": "Dwight Schrute",
    "discriminator": "9689",
    "email": "dwight.schrute@gmail.com",
    "status": "DO_NOT_DISTURB",
    "password": "$argon2id$v=19$m=4096,t=3,p=1$XXKWCX9/KZSJt494EwUZuw$YIMczsYEBBYEprEJsQdMH97E9NK0jTp0PV/sBu5mVZI",
    "phoneNumber": null,
    "createdAt": "2023-06-25 15:58:31.454",
    "chatGptRole": "Dwight Schrute from the US version of the TV show The Office",
    "avatarColor": "#e6005c"
  }
]